differently/__init__.py
differently/__main__.py
differently/cli.py
differently/deserialization.py
differently/difference_type.py
differently/exceptions.py
differently/json_differently.py
differently/list_differently.py
differently/py.typed
differently/string_differently.py
differently/text_differently.py
differently/yaml_differently.py
differently/version/VERSION
differently/version/__init__.py
differently/version/py.typed
differently-1.0.1.dist-info/LICENSE
differently-1.0.1.dist-info/METADATA
differently-1.0.1.dist-info/WHEEL
differently-1.0.1.dist-info/entry_points.txt
differently-1.0.1.dist-info/top_level.txt
differently-1.0.1.dist-info/RECORD
